<?xml version="1.0" encoding="UTF-8"?>
<!DOCTYPE properties SYSTEM "http://java.sun.com/dtd/properties.dtd">
<properties>

<!-- Application -->
	<entry key="application.title">NVK-Webshop</entry>

	<!-- Titles -->
	<entry key="titles.registration"> NVK-Shop : Regisztráció </entry>
	<entry key="titles.login"> NVK-shop : Bejelentkezés</entry>
	<entry key="titles.passwordReset"> NVK-Shop : Jelszó helyreállítás</entry>
	<entry key="titles.passwordRecover"> NVK-Shop :Új jelszó</entry>
	
	<!-- Login -->
	<entry key="login.failure">Hibás felhasználónév vagy jelszó!</entry>
 	<entry key="login.password">Jelszó</entry>
 	<entry key="login.userName">Felhasználó</entry>
 	<entry key="login.submit">Bejelentkezés</entry>
 	<entry key="login.title">Bejelentkezés</entry>

	<!-- Registration -->
	<entry key="registration.passwordConfirm">Kérjük adja meg újra jelszavát!</entry>
	<entry key="registration.passwordsNotMatch">A megadott jelszavak nem egyeznek!</entry>
	<entry key="registration.passwordMatch">A jelszavak egyeznek!</entry>
	<entry key="registration.registration">Regisztráció</entry>
	<entry key="registration.submit">Regisztráció véglegesítése</entry>
	<entry key="registration.success">Sikeresen regisztrált webshopunkra! A megadott email címre hamarosan küldünk egy aktivációs linket tartalmazó levelet. </entry>
 	<entry key="registration.invalidToken">A regisztráció aktivációja nem sikerült mivel a megadott token lejárt!</entry>
	<entry key="registration.activationSuccess">A regisztráció aktiválása sikerült! Mostmár bejelentkezhet fiókjába!</entry>
	<entry key="registration.sendRecovery">Jelszó helyreállító email küldése</entry>
	<entry key="registration.lostPasswordInfo">A jelszó helyreállító email kiküldéséhez kérjük adja meg korában  regisztrált email címmét</entry>
	<entry key="registration.passwordRecoverySent">A jelszó helyreállító email elküldésre került a megadott email címre!</entry>
	<entry key="registration.lostPassword">Jelszó helyreállítás</entry>
	<entry key="registration.passwordReseted">Az Ön jelszava helyreállításra került.</entry>
	<entry key="registration.permamentlyDeletedUser">Ez a fiók átmenetileg zárolásra került.</entry>
	<entry key="registration.invalidActivationCode">Az aktivációs kód helytelen!</entry>
	<entry key="registration.phoneNumber">Telefonszám</entry>
	<entry key="registration.userName">Felhasználónév</entry>
	<entry key="registration.firstName">Keresztnév</entry>
	<entry key="registration.lastName">Vezetéknév</entry>
	<entry key="registration.emailAlreadyRegistered">Ez az email-cím már regisztrálva van a rendszerünkben!Kérjük próbálja meg a jelszó helyreállítást.</entry>
	<entry key="registration.emailNotValid">Kérjük adjon meg egy valós email címmet!</entry>
	<entry key="registration.userNameAlreadyRegistered">Ez a felhasználónév már foglalt! Kérjük válasszon egy másikat.</entry>
	
	<entry key="validation.required">Kötelező mező!</entry>
	
	<entry key="outerBar.account">Account</entry>
	<entry key="outerBar.cart">Cart</entry>
	<entry key="outerBar.totalAmount">Total items</entry>
	<entry key="outerBar.logout">Logout</entry>
	<entry key="outerBar.cartAll">See all items</entry>
	<entry key="outerBar.orders">My orders</entry>

	<entry key="cart.totalPrice">Total price</entry>
	<entry key="amount.HUF">HUF</entry>

	<entry key="language.english">English</entry>
	<entry key="language.hungarian">Magyar</entry>

	<entry key="lostPassword.typeEmail">Kérjük írja be a már regisztrált email címmét hogy kiküldhessónk egy jelszó emlékeztető emailt!.</entry>
	<entry key="lostPassword.sendEmail">Küldés</entry>

	<entry key="validation.invalidOrExpiredToken">A kapott token érvénytele vagy lejárt! Kérjük próbálja meg a jelszó helyreállítást újra!</entry>
	<entry key="validation.passwordsNotMatch">A jelszavak nem eggyeznek!</entry>
	<entry key="passwordRecover.resetPassword">Jelszó helyreállítás</entry>



	<entry key="user.form">Felhasználó fiók</entry>
	<entry key="userEdit.changePassword">Jelszó csere</entry>
	<entry key="userEdit.password">Adja meg jelszavát újra:</entry>

	<entry key="user.wrongPassword">Hibás jelszó! Kérjük írja be újra!</entry>
	<entry key="user.passwordChanged">A jelszó sikeresen lecserélésre került!</entry>
	<entry key="user.saved">A mentések eltárolásra kerültek!</entry>

	<entry key="warning.alreadyLoggedIn">Már be van jelentkezve! Kérjük jelentkezzen ki előbb!</entry>

	<entry key="category.name">Kategória neve</entry>
	<entry key="category.subcategories">Alkategória</entry>
	<entry key="category.items">Termékek</entry>
	<entry key="category.addNewCategory">Új kategória</entry>
	<entry key="category.parent">Szülő </entry>
	<entry key="item.name">Temék neve</entry>
	<entry key="item.onStrock">Készlet</entry>
	<entry key="item.value">Érték</entry>
	<entry key="product.add">Újtermék</entry>
	<entry key="product.onStock">Készlet</entry>
	<entry key="product.price">Ár</entry>
	<entry key="titles.product">Termék kezelés</entry>
	<entry key="titles.products">Minden termék</entry>

	<entry key="prouduct.created">Termék létrehozva!</entry>
	<entry key="product.cantCreated">Termék nem hozható létre mivel a kategória elérhetetlen!</entry>
	<entry key="product.saved">Termék elmentve!</entry>
	<entry key="notFound.categoryOrProduct.">Termék vagy kategória nem található!</entry>
	<entry key="product.picture">Termék képe</entry>

	<entry key="general.qty">Mennyiség : </entry>
	<entry key="general.relatedProducts">Hasonló termékek</entry>
	<entry key="general.availability">Elérhetőség</entry>
	<entry key="general.moreInformation">Bővebb információ</entry>
	<entry key="general.addToCart">Kosárba</entry>
	<entry key="general.cartIsEmpty">Üres kosár :( </entry>
	<entry key="order.placed">Rendszerünk sikeresen feldolgozta rendelését!</entry>

	<entry key="general.product">Termék</entry>
	<entry key="navbar.allProducts">Minden termék</entry>
	<entry key="general.submitOrder">Rendelés leadása</entry>
	<entry key="menu.admin">Admin menü</entry>
	<entry key="general.categories">Kategóriák</entry>
<entry key="general.products">Termékek</entry>

</properties>